odoo_api/__init__.py
odoo_api/odoo.py
odoo_api-0.1.2.dist-info/WHEEL
odoo_api-0.1.2.dist-info/METADATA
odoo_api-0.1.2.dist-info/RECORD
