Metadata-Version: 2.1
Name: odoo-api
Version: 0.1.2
Summary: Api wrapper for Odoo 14.
Author: Jean-Paul Weijers
Author-email: jpweijers@users.noreply.github.com
Requires-Python: >=3.8,<4.0
Classifier: Programming Language :: Python :: 3
Classifier: Programming Language :: Python :: 3.10
Classifier: Programming Language :: Python :: 3.8
Classifier: Programming Language :: Python :: 3.9
Requires-Dist: aiohttp (>=3.8.1,<4.0.0)
Requires-Dist: requests (>=2.27.1,<3.0.0)
Requires-Dist: simplejson (>=3.17.6,<4.0.0)
